sjm/__init__.py
sjm/cli.py
sjm/client.py
sjm/exceptions.py
sjm/models.py
sjm/utils.py
sjm-1.0.4.dist-info/LICENSE
sjm-1.0.4.dist-info/METADATA
sjm-1.0.4.dist-info/WHEEL
sjm-1.0.4.dist-info/entry_points.txt
sjm-1.0.4.dist-info/top_level.txt
sjm-1.0.4.dist-info/RECORD
